crew_game/__init__.py
crew_game/core.py
crew_game/ui.py
crew_game/backend/__init__.py
crew_game/backend/main.py
crew_game/frontend/__init__.py
crew_game/frontend/main.py
crew_game-0.1.0.dist-info/entry_points.txt
crew_game-0.1.0.dist-info/LICENSE
crew_game-0.1.0.dist-info/WHEEL
crew_game-0.1.0.dist-info/METADATA
crew_game-0.1.0.dist-info/RECORD
